puzzle15_ai/__init__.py
puzzle15_ai/main_window.py
puzzle15_ai/node.py
puzzle15_ai/tree.py
puzzle15_ai/ui_mainwindow.py
puzzle15_ai-0.1.13.dist-info/LICENSE.md
puzzle15_ai-0.1.13.dist-info/METADATA
puzzle15_ai-0.1.13.dist-info/WHEEL
puzzle15_ai-0.1.13.dist-info/entry_points.txt
puzzle15_ai-0.1.13.dist-info/top_level.txt
puzzle15_ai-0.1.13.dist-info/RECORD
