Metadata-Version: 2.1
Name: puzzle15-ai
Version: 0.1.13
Summary: Puzzle15 AI solver
Home-page: https://github.com/SajjadAemmi/Puzzle15-AI
Author: Sajjad Aemmi
Author-email: sajjadaemmi@gmail.com
License-File: LICENSE.md
Requires-Dist: pyside6
Requires-Dist: numpy
